README.md
setup.cfg
setup.py
comeback/__init__.py
comeback/main.py
comeback/utils.py
comeback.egg-info/PKG-INFO
comeback.egg-info/SOURCES.txt
comeback.egg-info/dependency_links.txt
comeback.egg-info/entry_points.txt
comeback.egg-info/requires.txt
comeback.egg-info/top_level.txt