Metadata-Version: 1.1
Name: comeback
Version: 0.0.1
Summary: Comeback right to your project's last state
Home-page: https://github.com/agamm/comeback
Author: agamm
Author-email: UNKNOWN
License: MIT
Download-URL: https://github.com/agamm/comeback/archive/v0.0.2-alpha.tar.gz
Keywords: autorun,comeback,project restoration,auto open
Platform: UNKNOWN
Classifier: Development Status :: 3 - Alpha
Classifier: Intended Audience :: Developers
Classifier: Topic :: Software Development :: Build Tools
Classifier: License :: OSI Approved :: MIT License
Classifier: Programming Language :: Python :: 3
Classifier: Programming Language :: Python :: 3.6
